eganalyze/__init__.py
eganalyze/cli.py
eganalyze/lib.py
eganalyze/settings.py
eganalyze-1.0.4.dist-info/LICENSE
eganalyze-1.0.4.dist-info/METADATA
eganalyze-1.0.4.dist-info/WHEEL
eganalyze-1.0.4.dist-info/entry_points.txt
eganalyze-1.0.4.dist-info/top_level.txt
eganalyze-1.0.4.dist-info/RECORD
