Metadata-Version: 2.1
Name: eganalyze
Version: 1.0.4
Summary: UNKNOWN
Home-page: https://github.com/kennell/eganalyze
Author: Kevin Kennell
Author-email: kevin@kennell.de
License: MIT
Platform: UNKNOWN
Requires-Dist: click
Requires-Dist: pandas
